trickt/__init__.py
trickt-0.1.1.dist-info/entry_points.txt
trickt-0.1.1.dist-info/LICENSE
trickt-0.1.1.dist-info/WHEEL
trickt-0.1.1.dist-info/METADATA
trickt-0.1.1.dist-info/RECORD
