Metadata-Version: 2.1
Name: trickt
Version: 0.1.1
Summary: Search data for trickiness and obfuscation.
Home-page: https://github.com/krayzpipes/trickt
License: Apache-2.0
Keywords: security,obfuscate
Author: krayzpipes
Author-email: kylepiper29@gmail.com
Requires-Python: >=3.6,<4.0
Classifier: Intended Audience :: Information Technology
Classifier: License :: OSI Approved :: Apache Software License
Classifier: Programming Language :: Python :: 3
Classifier: Programming Language :: Python :: 3.6
Classifier: Programming Language :: Python :: 3.7
Classifier: Programming Language :: Python :: 3.8
Classifier: Topic :: Security
Project-URL: Repository, https://github.com/krayzpipes/trickt
